mypypkg/__init__.py
mypypkg/operations.py
gagan_mypkg-0.1.1.dist-info/METADATA
gagan_mypkg-0.1.1.dist-info/WHEEL
gagan_mypkg-0.1.1.dist-info/top_level.txt
gagan_mypkg-0.1.1.dist-info/RECORD
